PelerGUI/__init__.py
PelerGUI-0.0.1.dist-info/LICENSE
PelerGUI-0.0.1.dist-info/METADATA
PelerGUI-0.0.1.dist-info/WHEEL
PelerGUI-0.0.1.dist-info/top_level.txt
PelerGUI-0.0.1.dist-info/RECORD
