Metadata-Version: 2.1
Name: PelerGUI
Version: 0.0.1
Summary: A library that helps beginners to quickly and easily transfer their command line application to GUI application
Home-page: https://github.com/PelerYuan/PelerGUI
Author: Peler
Author-email: peler_little_pig@outlook.com
License: GPLv3
License-File: LICENSE
